[
    {"CountryCode": "DE", "StateCode": "NDS", "StateName": "Niedersachsen"},
    {"CountryCode": "DE", "StateCode": "BAW", "StateName": "Baden-Württemberg"},
    {"CountryCode": "DE", "StateCode": "BAY", "StateName": "Bayern"},
    {"CountryCode": "DE", "StateCode": "BER", "StateName": "Berlin"},
    {"CountryCode": "DE", "StateCode": "BRG", "StateName": "Brandenburg"},
    {"CountryCode": "DE", "StateCode": "BRE", "StateName": "Bremen"},
    {"CountryCode": "DE", "StateCode": "HAM", "StateName": "Hamburg"},
    {"CountryCode": "DE", "StateCode": "HES", "StateName": "Hessen"},
    {"CountryCode": "DE", "StateCode": "MEC", "StateName": "Mecklenburg-Vorpommern"},
    {"CountryCode": "DE", "StateCode": "NRW", "StateName": "Nordrhein-Westfalen"},
    {"CountryCode": "DE", "StateCode": "RHE", "StateName": "Rheinland-Pfalz"},
    {"CountryCode": "DE", "StateCode": "SAR", "StateName": "Saarland"},
    {"CountryCode": "DE", "StateCode": "SAS", "StateName": "Sachsen"},
    {"CountryCode": "DE", "StateCode": "SAC", "StateName": "Sachsen-Anhalt"},
    {"CountryCode": "DE", "StateCode": "SCN", "StateName": "Schleswig-Holstein"},
    {"CountryCode": "DE", "StateCode": "THE", "StateName": "Thüringen"}
]